Alt/ObjectLocalization/Constants/Inference.py
Alt/ObjectLocalization/Constants/Kalman.py
Alt/ObjectLocalization/Detections/DetectionPacket.py
Alt/ObjectLocalization/Detections/DetectionResult.py
Alt/ObjectLocalization/Detections/__init__.py
Alt/ObjectLocalization/Detections/detectionNetPacket.capnp
Alt/ObjectLocalization/Estimation/KalmanCache.py
Alt/ObjectLocalization/Estimation/KalmanEntry.py
Alt/ObjectLocalization/Estimation/KalmanLabeler.py
Alt/ObjectLocalization/Estimation/UKF.py
Alt/ObjectLocalization/Estimation/__init__.py
Alt/ObjectLocalization/Inference/ModelConfig.py
Alt/ObjectLocalization/Inference/MultiInferencer.py
Alt/ObjectLocalization/Inference/__init__.py
Alt/ObjectLocalization/Inference/inferencerBackend.py
Alt/ObjectLocalization/Inference/utils.py
Alt/ObjectLocalization/Inference/yolo11RknnUtils.py
Alt/ObjectLocalization/Inference/backends/TensorrtInferencer.py
Alt/ObjectLocalization/Inference/backends/onnxInferencer.py
Alt/ObjectLocalization/Inference/backends/rknnInferencer.py
Alt/ObjectLocalization/Inference/backends/ultralyticsInferencer.py
Alt/ObjectLocalization/Localization/DepthEstimationMethod.py
Alt/ObjectLocalization/Localization/LocalizationResult.py
Alt/ObjectLocalization/Localization/PipelineStep1.py
Alt/ObjectLocalization/Localization/PipelineStep2.py
Alt/ObjectLocalization/Localization/positionEstimator.py
Alt/ObjectLocalization/Localization/positionTranslations.py
Alt/ObjectLocalization/Localization/probmap.py
Alt/ObjectLocalization/Tracking/TrackedDetectionResult.py
Alt/ObjectLocalization/Tracking/__init__.py
Alt/ObjectLocalization/Tracking/baseTracker.py
Alt/ObjectLocalization/Tracking/deepSortBaseLabler.py
Alt/ObjectLocalization/Tracking/robotTracker.py
matrix_alt_objectlocalization-0.0.1.dist-info/licenses/LICENSE.txt
matrix_alt_objectlocalization-0.0.1.dist-info/METADATA
matrix_alt_objectlocalization-0.0.1.dist-info/WHEEL
matrix_alt_objectlocalization-0.0.1.dist-info/top_level.txt
matrix_alt_objectlocalization-0.0.1.dist-info/RECORD
